deputat/__init__.py
deputat/__main__.py
deputat/deputat.py
deputat/run.py
deputat/settings.py
deputat-0.2.4.dist-info/DESCRIPTION.rst
deputat-0.2.4.dist-info/METADATA
deputat-0.2.4.dist-info/RECORD
deputat-0.2.4.dist-info/WHEEL
deputat-0.2.4.dist-info/metadata.json
deputat-0.2.4.dist-info/top_level.txt
