Metadata-Version: 2.0
Name: deputat
Version: 0.2.4
Summary: deputat overview
Home-page: https://github.com/lfreist/deputat
Author: lfreist
Author-email: freist.leon@gmx.de
License: UNKNOWN
Platform: UNKNOWN
Classifier: Programming Language :: Python :: 3
Classifier: License :: OSI Approved :: MIT License
Classifier: Operating System :: OS Independent
Requires-Dist: PyQt5
